CHANGELOG.txt
LICENSE.txt
MANIFEST.in
README.rst
setup.cfg
setup.py
test/__init__.py
test/test_gcp.py
test/test_search.py
unicarbkb_glygen_api/__init__.py
unicarbkb_glygen_api/app.py
unicarbkb_glygen_api/mymath.py
unicarbkb_glygen_api.egg-info/PKG-INFO
unicarbkb_glygen_api.egg-info/SOURCES.txt
unicarbkb_glygen_api.egg-info/dependency_links.txt
unicarbkb_glygen_api.egg-info/entry_points.txt
unicarbkb_glygen_api.egg-info/not-zip-safe
unicarbkb_glygen_api.egg-info/requires.txt
unicarbkb_glygen_api.egg-info/top_level.txt