Metadata-Version: 1.1
Name: unicarbkb-glygen-api
Version: 0.5
Summary: restful api to query structure, glycoprotein, and publications
Home-page: UNKNOWN
Author: Matthew Campbell
Author-email: m.campbell2@griffith.edu.au
License: MIT
Keywords: unicarbkb glygen restful api
Platform: UNKNOWN
Classifier: Development Status :: 1 - Planning
Classifier: Programming Language :: Python
